py_telegram_sender/__init__.py
py_telegram_sender/core.py
py_telegram_sender-0.1.3.dist-info/LICENSE
py_telegram_sender-0.1.3.dist-info/METADATA
py_telegram_sender-0.1.3.dist-info/WHEEL
py_telegram_sender-0.1.3.dist-info/top_level.txt
py_telegram_sender-0.1.3.dist-info/RECORD
