Metadata-Version: 2.1
Name: py-telegram-sender
Version: 0.1.3
Summary: A simple library for sending messages and files via Telegram
Home-page: https://github.com/au11n/py-telegram-sender
Author: Nikita Aull
Author-email: aull.nikita.i@gmail.com
Classifier: Programming Language :: Python :: 3
Classifier: License :: OSI Approved :: MIT License
Classifier: Operating System :: OS Independent
Requires-Python: >=3.6
License-File: LICENSE
Requires-Dist: requests
